starlette_gzip_request/__init__.py
starlette_gzip_request/middleware.py
starlette_gzip_request-0.1.0.dist-info/METADATA
starlette_gzip_request-0.1.0.dist-info/WHEEL
starlette_gzip_request-0.1.0.dist-info/licenses/LICENSE
starlette_gzip_request-0.1.0.dist-info/RECORD
